saguaro/__init__.py
saguaro/core/__init__.py
saguaro/core/constants.py
saguaro/core/context.py
saguaro/core/engine.py
saguaro/memory/__init__.py
saguaro/memory/base.py
saguaro/memory/markdown_store.py
saguaro/memory/schema.py
saguaro/memory/smart_store.py
saguaro/models/__init__.py
saguaro/models/factory.py
saguaro/senses/__init__.py
saguaro/senses/inputs.py
saguaro/senses/visual.py
saguaro/tools/__init__.py
saguaro/tools/memory_tools.py
saguaro-0.2.0.dist-info/licenses/LICENSE
saguaro-0.2.0.dist-info/METADATA
saguaro-0.2.0.dist-info/WHEEL
saguaro-0.2.0.dist-info/top_level.txt
saguaro-0.2.0.dist-info/RECORD
