Metadata-Version: 2.4
Name: saguaro
Version: 0.2.0
Summary: A neuro-symbolic proactive OS library.
Author: Omkar Mamidpalliwar
License: MIT License
Project-URL: Homepage, https://github.com/coolguy2982/saguaro
Project-URL: Bug Tracker, https://github.com/coolguy2982/saguaro/issues
Classifier: Programming Language :: Python :: 3
Classifier: License :: OSI Approved :: MIT License
Classifier: Operating System :: OS Independent
Requires-Python: >=3.9
License-File: LICENSE
Requires-Dist: google-adk>=0.1.0
Requires-Dist: litellm
Requires-Dist: pydantic
Requires-Dist: mss
Requires-Dist: Pillow
Requires-Dist: pynput
Dynamic: license-file
